README.md
setup.cfg
setup.py
wjf_tools/ConfusionMatrix.py
wjf_tools/DataProcess.py
wjf_tools/NiuNiuTools.py
wjf_tools/__init__.py
wjf_tools/detect_by_cv.py
wjf_tools.egg-info/PKG-INFO
wjf_tools.egg-info/SOURCES.txt
wjf_tools.egg-info/dependency_links.txt
wjf_tools.egg-info/requires.txt
wjf_tools.egg-info/top_level.txt