Metadata-Version: 2.1
Name: wjf-tools
Version: 0.1.3
Summary: all kinds of API
Home-page: 
Download-URL: 
Author: Jinfang Wei
Author-email: 2295542405@qq.com
License: MIT
Keywords: API,tools,Python
Classifier: Development Status :: 3 - Alpha
Classifier: Intended Audience :: Developers
Classifier: Topic :: Software Development :: Build Tools
Classifier: License :: OSI Approved :: MIT License
Classifier: Programming Language :: Python :: 3.7
